shipkit/__init__.py
shipkit/backend.py
shipkit/cli.py
shipkit/config.py
shipkit-0.0.1.dist-info/licenses/LICENSE
shipkit-0.0.1.dist-info/METADATA
shipkit-0.0.1.dist-info/WHEEL
shipkit-0.0.1.dist-info/top_level.txt
shipkit-0.0.1.dist-info/RECORD
